coco2customvision/__init__.py
coco2customvision/__main__.py
coco2customvision/_dist_ver.py
coco2customvision/azure_blob.py
coco2customvision/cli.py
coco2customvision/coco.py
coco2customvision/custom_vision.py
coco2customvision/export_coco.py
coco2customvision/import_coco.py
coco2customvision/integration.py
coco2customvision/utils.py
coco2customvision/version.py
coco2customvision-0.0.1.dist-info/LICENSE
coco2customvision-0.0.1.dist-info/METADATA
coco2customvision-0.0.1.dist-info/WHEEL
coco2customvision-0.0.1.dist-info/entry_points.txt
coco2customvision-0.0.1.dist-info/top_level.txt
coco2customvision-0.0.1.dist-info/RECORD
