Metadata-Version: 2.1
Name: coco2customvision
Version: 0.0.1
Summary: Tool to backup custom vision projects to COCO files and vise versa
Home-page: https://github.com/rndazurescript/Coco2CustomVision
Maintainer: RnD Azure Script
Maintainer-email: rndazurescript@users.noreply.github.com
License: MIT
Keywords: custom-vision,coco,blob-storage,backup,azure
Platform: any
Classifier: Environment :: Console
Classifier: License :: OSI Approved :: MIT License
Classifier: Programming Language :: Python :: 3
Classifier: Programming Language :: Python :: 3 :: Only
Classifier: Programming Language :: Python :: 3.6
Classifier: Programming Language :: Python :: 3.7
Classifier: Programming Language :: Python :: 3.8
Classifier: Programming Language :: Python :: 3.9
Classifier: Topic :: System :: Archiving :: Backup
Requires-Python: >=3.6
License-File: LICENSE
Requires-Dist: azure-cognitiveservices-vision-customvision (>=3)
Requires-Dist: azure.storage.blob (>=12)
Requires-Dist: click (>=8)
Requires-Dist: tqdm (>=4)
Provides-Extra: dev
Requires-Dist: black ; extra == 'dev'
Requires-Dist: flake8 ; extra == 'dev'
Requires-Dist: pytest ; extra == 'dev'
Requires-Dist: pytest-env ; extra == 'dev'
Requires-Dist: setup-cfg-fmt ; extra == 'dev'
Requires-Dist: setuptools-scm ; extra == 'dev'
